nonebot_plugin_who_is_spy/__init__.py
nonebot_plugin_who_is_spy/config.py
nonebot_plugin_who_is_spy-0.0.4.dist-info/licenses/LICENSE
nonebot_plugin_who_is_spy-0.0.4.dist-info/WHEEL
nonebot_plugin_who_is_spy-0.0.4.dist-info/METADATA
nonebot_plugin_who_is_spy-0.0.4.dist-info/RECORD
