Metadata-Version: 2.4
Name: nonebot_plugin_who_is_spy
Version: 0.0.4
Summary: 一款适用于QQ群的谁是卧底小游戏插件
Author-email: Hanserprpr <2041283903@qq.com>
Requires-Python: >=3.8
License-File: LICENSE
Requires-Dist: nonebot2>=2.3.0
Requires-Dist: nonebot-adapter-onebot>=2.0.0
Requires-Dist: nonebot-plugin-localstore>=0.5.1
Project-URL: Home, https://github.com/Hanserprpr/nonebot-plugin-who-is-spy
